mcp_web_gateway/__init__.py
mcp_web_gateway/components.py
mcp_web_gateway/routing.py
mcp_web_gateway/server.py
mcp_web_gateway-0.0.0.dev0.dist-info/METADATA
mcp_web_gateway-0.0.0.dev0.dist-info/WHEEL
mcp_web_gateway-0.0.0.dev0.dist-info/RECORD
