Metadata-Version: 2.4
Name: mcp-web-gateway
Version: 0.0.0.dev0
Summary: Connecting MCP Agents to 100s of Web Services 
Project-URL: Homepage, https://github.com/chughtapan/mcp-web-gateway
Project-URL: Bug Reports, https://github.com/chughtapan/mcp-web-gateway/issues
Project-URL: Source, https://github.com/chughtapan/mcp-web-gateway
Author-email: Tapan Chugh <chugh.tapan@gmail.com>
License: MIT
Classifier: Development Status :: 3 - Alpha
Classifier: Intended Audience :: Developers
Classifier: License :: OSI Approved :: MIT License
Classifier: Programming Language :: Python :: 3
Classifier: Programming Language :: Python :: 3.12
Requires-Python: >=3.12
Requires-Dist: fastmcp>=2.11.0
Requires-Dist: httpx>=0.26.0
Provides-Extra: agent
Requires-Dist: fast-agent-mcp>=0.2.46; extra == 'agent'
Provides-Extra: dev
Requires-Dist: fastapi>=0.100.0; extra == 'dev'
Requires-Dist: pytest-asyncio>=0.24.0; extra == 'dev'
Requires-Dist: pytest-httpx>=0.30.0; extra == 'dev'
Requires-Dist: pytest>=8.0.0; extra == 'dev'
